{
  "base_price": 1950,
  "beamstation_catalog_url": "https://beamstation.com/datasets",
  "beamstation_origin": "https://beamstation.com",
  "category_group_name": "Restaurants",
  "config_category": "census",
  "config_description": "Complete dataset of all active restaurant listings in Cape Coral, Florida with a population of over 194k. Filtered by the Restaurants category group, providing business profiles, review counts, contact information, and competitive benchmarks. Refreshed weekly.",
  "config_name": "All Restaurants in Cape Coral, Florida, US",
  "export_job_id": "22af316b-6837-42e8-a1db-32fac9df6c80",
  "github_org": "Beamstation-Datasets",
  "id_short": 432880,
  "location_name": "Cape Coral",
  "location_type": "city",
  "repo_name": "all-restaurants-in-cape-coral-florida-us-sample-432880",
  "sample_b2_path": "b2-export:BeamStation-ExportFiles/432880/beamstation_432880_restaurants-us-fl_SAMPLE_DIST.csv",
  "sample_pct": 9.95,
  "sample_records": 60,
  "sample_sha256": "ecd937c6d3c7234832a5b3a9f1b9e4b2386753515c755c0e9915eba18f19b0b8",
  "sample_size_bytes": 222768,
  "total_records": 603,
  "updated_at": "2026-04-28T11:31:42.785831+00:00"
}